<?xml version="1.0" encoding="UTF-8"?>
<item><pubDate>Wed, 08 May 2019 11:45:06 +0300</pubDate><creDate>Wed, 08 May 2019 11:25:31 +0300</creDate><title><![CDATA[ВАЖЛИВА КОНСУЛЬТАЦІЯ]]></title><url><![CDATA[consulting-20190508-1125]]></url><metad><![CDATA[]]></metad><content><![CDATA[&lt;p&gt;Компанія IT-Cube радить не ставити чашку кави на теку дисководу, інша справа чай&lt;/p&gt;
]]></content><author><![CDATA[admin]]></author><user><![CDATA[admin]]></user><special><![CDATA[consulting]]></special><meta><![CDATA[consulting, _special_consulting]]></meta><template><![CDATA[template.php]]></template><parent><![CDATA[consulting]]></parent><menuOrder><![CDATA[3]]></menuOrder><menu><![CDATA[consulting]]></menu><menuStatus><![CDATA[]]></menuStatus><private><![CDATA[]]></private></item>
